easygamechat/__init__.py
easygamechat/easygamechat.py
easygamechat-0.3.0.dist-info/METADATA
easygamechat-0.3.0.dist-info/WHEEL
easygamechat-0.3.0.dist-info/top_level.txt
easygamechat-0.3.0.dist-info/RECORD
