Metadata-Version: 2.4
Name: easygamechat
Version: 0.3.0
Summary: An easy and secure Python library for real-time game chat
Author-email: Fabio Ardis <fabioardis@email.com>
License-Expression: MIT
Project-URL: Homepage, https://github.com/FabioArdis/EasyGameChat
Keywords: chat,game,networking,client,multiplayer
Classifier: Development Status :: 4 - Beta
Classifier: Intended Audience :: Developers
Classifier: Topic :: Games/Entertainment
Classifier: Topic :: Communications :: Chat
Classifier: Programming Language :: Python :: 3
Classifier: Programming Language :: Python :: 3.7
Classifier: Programming Language :: Python :: 3.8
Classifier: Programming Language :: Python :: 3.9
Classifier: Programming Language :: Python :: 3.10
Classifier: Programming Language :: Python :: 3.11
Requires-Python: >=3.7
